Rookify-1.1.0.data/data/docs/LICENSE
Rookify-1.1.0.data/data/docs/README.md
rookify/__init__.py
rookify/__main__.py
rookify/config.schema.yaml
rookify/logger.py
rookify/yaml.py
rookify/modules/__init__.py
rookify/modules/ceph.py
rookify/modules/exception.py
rookify/modules/k8s.py
rookify/modules/machine.py
rookify/modules/module.py
rookify/modules/ssh.py
rookify/modules/template.py
rookify/modules/analyze_ceph/__init__.py
rookify/modules/analyze_ceph/main.py
rookify/modules/cephx_auth_config/__init__.py
rookify/modules/cephx_auth_config/main.py
rookify/modules/create_rook_cluster/__init__.py
rookify/modules/create_rook_cluster/main.py
rookify/modules/create_rook_cluster/templates/cluster.yaml.j2
rookify/modules/create_rook_resources/__init__.py
rookify/modules/create_rook_resources/main.py
rookify/modules/example/__init__.py
rookify/modules/example/main.py
rookify/modules/k8s_prerequisites_check/__init__.py
rookify/modules/k8s_prerequisites_check/main.py
rookify/modules/migrate_mds/__init__.py
rookify/modules/migrate_mds/main.py
rookify/modules/migrate_mds_pools/__init__.py
rookify/modules/migrate_mds_pools/main.py
rookify/modules/migrate_mds_pools/templates/filesystem.yaml.j2
rookify/modules/migrate_mgrs/__init__.py
rookify/modules/migrate_mgrs/main.py
rookify/modules/migrate_mons/__init__.py
rookify/modules/migrate_mons/main.py
rookify/modules/migrate_osd_pools/__init__.py
rookify/modules/migrate_osd_pools/main.py
rookify/modules/migrate_osd_pools/templates/pool.yaml.j2
rookify/modules/migrate_osds/__init__.py
rookify/modules/migrate_osds/main.py
rookify/modules/migrate_osds/templates/nodes_osd_devices_patch.yaml.j2
rookify/modules/migrate_rgw_pools/__init__.py
rookify/modules/migrate_rgw_pools/main.py
rookify/modules/migrate_rgw_pools/templates/pool.yaml.j2
rookify/modules/migrate_rgws/__init__.py
rookify/modules/migrate_rgws/main.py
rookify/modules/osism_configuration/__init__.py
rookify/modules/osism_configuration/main.py
Rookify-1.1.0.dist-info/LICENSE
Rookify-1.1.0.dist-info/METADATA
Rookify-1.1.0.dist-info/WHEEL
Rookify-1.1.0.dist-info/entry_points.txt
Rookify-1.1.0.dist-info/top_level.txt
Rookify-1.1.0.dist-info/RECORD
