Metadata-Version: 2.1
Name: Rookify
Version: 1.1.0
Summary: Enable Ceph-Cluster migrations to Rook
Author-email: Sovereign Cloud Stack Developers <scs@osb-alliance.com>
License:                                  Apache License
Project-URL: Homepage, https://scs.community
Platform: any
Classifier: Intended Audience :: System Administrators
Classifier: License :: OSI Approved :: Apache Software License
Classifier: Operating System :: OS Independent
Classifier: Programming Language :: Python
Classifier: Environment :: Console
Classifier: Topic :: System :: Clustering
Classifier: Topic :: System :: Systems Administration
Classifier: Topic :: Utilities
Requires-Python: >=3.9
License-File: LICENSE
Requires-Dist: bcrypt==4.1.2
Requires-Dist: cachetools==5.3.2
Requires-Dist: certifi==2024.7.4
Requires-Dist: cffi==1.16.0
Requires-Dist: charset-normalizer==3.3.2
Requires-Dist: cryptography==43.0.1
Requires-Dist: dill==0.3.8
Requires-Dist: decorator==5.1.1
Requires-Dist: Deprecated==1.2.14
Requires-Dist: fabric==3.2.2
Requires-Dist: google-auth==2.28.1
Requires-Dist: idna==3.7
Requires-Dist: invoke==2.2.0
Requires-Dist: Jinja2==3.1.4
Requires-Dist: kubernetes==29.0.0
Requires-Dist: MarkupSafe==2.1.5
Requires-Dist: oauthlib==3.2.2
Requires-Dist: paramiko==3.4.0
Requires-Dist: pyasn1==0.5.1
Requires-Dist: pyasn1-modules==0.3.0
Requires-Dist: pycparser==2.21
Requires-Dist: PyNaCl==1.5.0
Requires-Dist: python-dateutil==2.8.2
Requires-Dist: PyYAML==6.0.1
Requires-Dist: requests==2.32.2
Requires-Dist: requests-oauthlib==1.3.1
Requires-Dist: rsa==4.9
Requires-Dist: six==1.16.0
Requires-Dist: structlog==24.1.0
Requires-Dist: transitions==0.9.0
Requires-Dist: urllib3==2.2.2
Requires-Dist: yamale==5.1.0
Requires-Dist: websocket-client==1.7.0
Requires-Dist: wrapt==1.16.0
Requires-Dist: pytest==8.0.2
Requires-Dist: pytest-structlog==1.1
Provides-Extra: tests
Requires-Dist: pytest==8.0.2; extra == "tests"
